setup.py
imagescanner/__init__.py
imagescanner/settings.py
imagescanner.egg-info/PKG-INFO
imagescanner.egg-info/SOURCES.txt
imagescanner.egg-info/dependency_links.txt
imagescanner.egg-info/requires.txt
imagescanner.egg-info/top_level.txt
imagescanner/backends/__init__.py
imagescanner/backends/base/__init__.py
imagescanner/backends/net/__init__.py
imagescanner/backends/sane/__init__.py
imagescanner/backends/test/__init__.py
imagescanner/backends/test/data/__init__.py
imagescanner/backends/twain/__init__.py
imagescanner/core/__init__.py
imagescanner/core/_imagescanner.py
imagescanner/core/server.py
imagescanner/utils/__init__.py
imagescanner/utils/logger.py