Metadata-Version: 1.0
Name: imagescanner
Version: 0.9
Summary: Multi-platform Python library to access scanner devices.
Home-page: http://code.google.com/p/imagescanner/
Author: Sergio Oliveira
Author-email: seocam@seocam.com
License: UNKNOWN
Platform: UNKNOWN
